{"sleep":[{"dateOfSleep":"2018-02-09","duration":32400000,"efficiency":95,"endTime":"2018-02-09T08:53:30.000","infoCode":0,"isMainSleep":true,"levels":{"data":[{"dateTime":"2018-02-08T23:53:00.000","level":"wake","seconds":1080},{"dateTime":"2018-02-09T00:11:00.000","level":"light","seconds":120},{"dateTime":"2018-02-09T00:13:00.000","level":"wake","seconds":390},{"dateTime":"2018-02-09T00:19:30.000","level":"light","seconds":2400},{"dateTime":"2018-02-09T00:59:30.000","level":"deep","seconds":3060},{"dateTime":"2018-02-09T01:50:30.000","level":"light","seconds":2250},{"dateTime":"2018-02-09T02:28:00.000","level":"deep","seconds":450},{"dateTime":"2018-02-09T02:35:30.000","level":"light","seconds":360},{"dateTime":"2018-02-09T02:41:30.000","level":"deep","seconds":960},{"dateTime":"2018-02-09T02:57:30.000","level":"light","seconds":1200},{"dateTime":"2018-02-09T03:17:30.000","level":"deep","seconds":450},{"dateTime":"2018-02-09T03:25:00.000","level":"light","seconds":2340},{"dateTime":"2018-02-09T04:04:00.000","level":"rem","seconds":420},{"dateTime":"2018-02-09T04:11:00.000","level":"light","seconds":750},{"dateTime":"2018-02-09T04:23:30.000","level":"rem","seconds":270},{"dateTime":"2018-02-09T04:28:00.000","level":"light","seconds":1950},{"dateTime":"2018-02-09T05:00:30.000","level":"deep","seconds":600},{"dateTime":"2018-02-09T05:10:30.000","level":"light","seconds":3000},{"dateTime":"2018-02-09T06:00:30.000","level":"rem","seconds":750},{"dateTime":"2018-02-09T06:13:00.000","level":"wake","seconds":540},{"dateTime":"2018-02-09T06:22:00.000","level":"light","seconds":3600},{"dateTime":"2018-02-09T07:22:00.000","level":"rem","seconds":1590},{"dateTime":"2018-02-09T07:48:30.000","level":"light","seconds":600},{"dateTime":"2018-02-09T07:58:30.000","level":"rem","seconds":1680},{"dateTime":"2018-02-09T08:26:30.000","level":"light","seconds":390},{"dateTime":"2018-02-09T08:33:00.000","level":"wake","seconds":330},{"dateTime":"2018-02-09T08:38:30.000","level":"light","seconds":630},{"dateTime":"2018-02-09T08:49:00.000","level":"wake","seconds":270}],"shortData":[{"dateTime":"2018-02-09T00:22:00.000","level":"wake","seconds":120},{"dateTime":"2018-02-09T00:29:00.000","level":"wake","seconds":120},{"dateTime":"2018-02-09T01:50:00.000","level":"wake","seconds":30},{"dateTime":"2018-02-09T01:53:00.000","level":"wake","seconds":120},{"dateTime":"2018-02-09T02:12:30.000","level":"wake","seconds":30},{"dateTime":"2018-02-09T03:33:30.000","level":"wake","seconds":30},{"dateTime":"2018-02-09T04:09:30.000","level":"wake","seconds":90},{"dateTime":"2018-02-09T04:14:00.000","level":"wake","seconds":60},{"dateTime":"2018-02-09T05:22:00.000","level":"wake","seconds":60},{"dateTime":"2018-02-09T05:48:30.000","level":"wake","seconds":30},{"dateTime":"2018-02-09T06:24:00.000","level":"wake","seconds":30},{"dateTime":"2018-02-09T06:48:30.000","level":"wake","seconds":30},{"dateTime":"2018-02-09T07:00:00.000","level":"wake","seconds":90},{"dateTime":"2018-02-09T07:07:00.000","level":"wake","seconds":30},{"dateTime":"2018-02-09T07:46:00.000","level":"wake","seconds":30},{"dateTime":"2018-02-09T08:29:00.000","level":"wake","seconds":90}],"summary":{"deep":{"count":5,"minutes":92,"thirtyDayAvgMinutes":94},"light":{"count":26,"minutes":312,"thirtyDayAvgMinutes":286},"rem":{"count":6,"minutes":76,"thirtyDayAvgMinutes":94},"wake":{"count":21,"minutes":60,"thirtyDayAvgMinutes":58}}},"logId":17184606124,"minutesAfterWakeup":0,"minutesAsleep":480,"minutesAwake":60,"minutesToFallAsleep":0,"startTime":"2018-02-08T23:53:00.000","timeInBed":540,"type":"stages"}],"summary":{"stages":{"deep":58,"light":287,"rem":100,"wake":48},"totalMinutesAsleep":480,"totalSleepRecords":1,"totalTimeInBed":540},"fitbit-rate-limit-limit":"150","fitbit-rate-limit-remaining":"118","fitbit-rate-limit-reset":"2153"}