{"sleep":[{"dateOfSleep":"2018-03-19","duration":7260000,"efficiency":92,"endTime":"2018-03-19T14:53:30.000","infoCode":2,"isMainSleep":false,"levels":{"data":[{"dateTime":"2018-03-19T12:52:30.000","level":"asleep","seconds":180},{"dateTime":"2018-03-19T12:55:30.000","level":"restless","seconds":120},{"dateTime":"2018-03-19T12:57:30.000","level":"awake","seconds":60},{"dateTime":"2018-03-19T12:58:30.000","level":"asleep","seconds":360},{"dateTime":"2018-03-19T13:04:30.000","level":"restless","seconds":120},{"dateTime":"2018-03-19T13:06:30.000","level":"asleep","seconds":3540},{"dateTime":"2018-03-19T14:05:30.000","level":"restless","seconds":120},{"dateTime":"2018-03-19T14:07:30.000","level":"asleep","seconds":2340},{"dateTime":"2018-03-19T14:46:30.000","level":"restless","seconds":240},{"dateTime":"2018-03-19T14:50:30.000","level":"asleep","seconds":180}],"summary":{"asleep":{"count":0,"minutes":111},"awake":{"count":1,"minutes":1},"restless":{"count":4,"minutes":9}}},"logId":17603550508,"minutesAfterWakeup":0,"minutesAsleep":111,"minutesAwake":10,"minutesToFallAsleep":0,"startTime":"2018-03-19T12:52:30.000","timeInBed":121,"type":"classic"},{"dateOfSleep":"2018-03-19","duration":36840000,"efficiency":98,"endTime":"2018-03-19T11:18:30.000","infoCode":1,"isMainSleep":true,"levels":{"data":[{"dateTime":"2018-03-19T01:04:30.000","level":"asleep","seconds":60},{"dateTime":"2018-03-19T01:05:30.000","level":"restless","seconds":60},{"dateTime":"2018-03-19T01:06:30.000","level":"asleep","seconds":1860},{"dateTime":"2018-03-19T01:37:30.000","level":"restless","seconds":120},{"dateTime":"2018-03-19T01:39:30.000","level":"asleep","seconds":3540},{"dateTime":"2018-03-19T02:38:30.000","level":"restless","seconds":60},{"dateTime":"2018-03-19T02:39:30.000","level":"asleep","seconds":6420},{"dateTime":"2018-03-19T04:26:30.000","level":"restless","seconds":60},{"dateTime":"2018-03-19T04:27:30.000","level":"asleep","seconds":17460},{"dateTime":"2018-03-19T09:18:30.000","level":"restless","seconds":240},{"dateTime":"2018-03-19T09:22:30.000","level":"awake","seconds":120},{"dateTime":"2018-03-19T09:24:30.000","level":"restless","seconds":60},{"dateTime":"2018-03-19T09:25:30.000","level":"asleep","seconds":4140},{"dateTime":"2018-03-19T10:34:30.000","level":"restless","seconds":60},{"dateTime":"2018-03-19T10:35:30.000","level":"asleep","seconds":2580}],"summary":{"asleep":{"count":0,"minutes":601},"awake":{"count":1,"minutes":2},"restless":{"count":7,"minutes":11}}},"logId":17603550507,"minutesAfterWakeup":0,"minutesAsleep":601,"minutesAwake":13,"minutesToFallAsleep":0,"startTime":"2018-03-19T01:04:30.000","timeInBed":614,"type":"classic"}],"summary":{"stages":{"deep":0,"light":0,"rem":0,"wake":0},"totalMinutesAsleep":712,"totalSleepRecords":2,"totalTimeInBed":735},"fitbit-rate-limit-limit":"150","fitbit-rate-limit-remaining":"128","fitbit-rate-limit-reset":"1732"}