{"sleep":[{"dateOfSleep":"2018-06-18","duration":29460000,"efficiency":91,"endTime":"2018-06-18T08:09:30.000","infoCode":0,"isMainSleep":true,"levels":{"data":[{"dateTime":"2018-06-17T23:58:30.000","level":"wake","seconds":30},{"dateTime":"2018-06-17T23:59:00.000","level":"light","seconds":330},{"dateTime":"2018-06-18T00:04:30.000","level":"wake","seconds":690},{"dateTime":"2018-06-18T00:16:00.000","level":"light","seconds":120},{"dateTime":"2018-06-18T00:18:00.000","level":"wake","seconds":420},{"dateTime":"2018-06-18T00:25:00.000","level":"light","seconds":270},{"dateTime":"2018-06-18T00:29:30.000","level":"deep","seconds":1230},{"dateTime":"2018-06-18T00:50:00.000","level":"light","seconds":1020},{"dateTime":"2018-06-18T01:07:00.000","level":"deep","seconds":720},{"dateTime":"2018-06-18T01:19:00.000","level":"light","seconds":840},{"dateTime":"2018-06-18T01:33:00.000","level":"deep","seconds":480},{"dateTime":"2018-06-18T01:41:00.000","level":"light","seconds":5100},{"dateTime":"2018-06-18T03:06:00.000","level":"rem","seconds":300},{"dateTime":"2018-06-18T03:11:00.000","level":"light","seconds":1230},{"dateTime":"2018-06-18T03:31:30.000","level":"rem","seconds":1380},{"dateTime":"2018-06-18T03:54:30.000","level":"wake","seconds":450},{"dateTime":"2018-06-18T04:02:00.000","level":"light","seconds":780},{"dateTime":"2018-06-18T04:15:00.000","level":"wake","seconds":1080},{"dateTime":"2018-06-18T04:33:00.000","level":"light","seconds":180},{"dateTime":"2018-06-18T04:36:00.000","level":"wake","seconds":420},{"dateTime":"2018-06-18T04:43:00.000","level":"light","seconds":510},{"dateTime":"2018-06-18T04:51:30.000","level":"deep","seconds":1650},{"dateTime":"2018-06-18T05:19:00.000","level":"light","seconds":1080},{"dateTime":"2018-06-18T05:37:00.000","level":"wake","seconds":270},{"dateTime":"2018-06-18T05:41:30.000","level":"light","seconds":1710},{"dateTime":"2018-06-18T06:10:00.000","level":"rem","seconds":2430},{"dateTime":"2018-06-18T06:50:30.000","level":"light","seconds":1770},{"dateTime":"2018-06-18T07:20:00.000","level":"deep","seconds":270},{"dateTime":"2018-06-18T07:24:30.000","level":"rem","seconds":750},{"dateTime":"2018-06-18T07:37:00.000","level":"light","seconds":1950}],"shortData":[{"dateTime":"2018-06-18T00:49:00.000","level":"wake","seconds":60},{"dateTime":"2018-06-18T00:55:00.000","level":"wake","seconds":30},{"dateTime":"2018-06-18T01:21:00.000","level":"wake","seconds":120},{"dateTime":"2018-06-18T01:42:30.000","level":"wake","seconds":150},{"dateTime":"2018-06-18T02:03:00.000","level":"wake","seconds":30},{"dateTime":"2018-06-18T02:11:30.000","level":"wake","seconds":30},{"dateTime":"2018-06-18T02:25:00.000","level":"wake","seconds":30},{"dateTime":"2018-06-18T02:28:00.000","level":"wake","seconds":30},{"dateTime":"2018-06-18T02:32:00.000","level":"wake","seconds":60},{"dateTime":"2018-06-18T03:27:30.000","level":"wake","seconds":30},{"dateTime":"2018-06-18T03:34:30.000","level":"wake","seconds":30},{"dateTime":"2018-06-18T03:50:00.000","level":"wake","seconds":30},{"dateTime":"2018-06-18T04:05:00.000","level":"wake","seconds":120},{"dateTime":"2018-06-18T04:10:30.000","level":"wake","seconds":120},{"dateTime":"2018-06-18T05:32:30.000","level":"wake","seconds":30},{"dateTime":"2018-06-18T06:35:30.000","level":"wake","seconds":30},{"dateTime":"2018-06-18T08:03:30.000","level":"wake","seconds":30}],"summary":{"deep":{"count":5,"minutes":71,"thirtyDayAvgMinutes":91},"light":{"count":27,"minutes":265,"thirtyDayAvgMinutes":262},"rem":{"count":7,"minutes":80,"thirtyDayAvgMinutes":106},"wake":{"count":24,"minutes":75,"thirtyDayAvgMinutes":60}}},"logId":18580723997,"minutesAfterWakeup":0,"minutesAsleep":416,"minutesAwake":75,"minutesToFallAsleep":0,"startTime":"2018-06-17T23:58:30.000","timeInBed":491,"type":"stages"}],"summary":{"stages":{"deep":79,"light":192,"rem":156,"wake":56},"totalMinutesAsleep":416,"totalSleepRecords":1,"totalTimeInBed":491},"fitbit-rate-limit-limit":"150","fitbit-rate-limit-remaining":"38","fitbit-rate-limit-reset":"1113"}