{"sleep":[{"dateOfSleep":"2018-06-04","duration":29220000,"efficiency":95,"endTime":"2018-06-04T08:48:00.000","infoCode":1,"isMainSleep":true,"levels":{"data":[{"dateTime":"2018-06-04T00:41:00.000","level":"restless","seconds":60},{"dateTime":"2018-06-04T00:42:00.000","level":"awake","seconds":180},{"dateTime":"2018-06-04T00:45:00.000","level":"restless","seconds":60},{"dateTime":"2018-06-04T00:46:00.000","level":"asleep","seconds":2460},{"dateTime":"2018-06-04T01:27:00.000","level":"restless","seconds":60},{"dateTime":"2018-06-04T01:28:00.000","level":"asleep","seconds":180},{"dateTime":"2018-06-04T01:31:00.000","level":"restless","seconds":60},{"dateTime":"2018-06-04T01:32:00.000","level":"asleep","seconds":3120},{"dateTime":"2018-06-04T02:24:00.000","level":"restless","seconds":120},{"dateTime":"2018-06-04T02:26:00.000","level":"asleep","seconds":120},{"dateTime":"2018-06-04T02:28:00.000","level":"restless","seconds":60},{"dateTime":"2018-06-04T02:29:00.000","level":"asleep","seconds":2580},{"dateTime":"2018-06-04T03:12:00.000","level":"restless","seconds":180},{"dateTime":"2018-06-04T03:15:00.000","level":"asleep","seconds":480},{"dateTime":"2018-06-04T03:23:00.000","level":"restless","seconds":120},{"dateTime":"2018-06-04T03:25:00.000","level":"asleep","seconds":120},{"dateTime":"2018-06-04T03:27:00.000","level":"restless","seconds":60},{"dateTime":"2018-06-04T03:28:00.000","level":"asleep","seconds":6120},{"dateTime":"2018-06-04T05:10:00.000","level":"restless","seconds":60},{"dateTime":"2018-06-04T05:11:00.000","level":"asleep","seconds":6420},{"dateTime":"2018-06-04T06:58:00.000","level":"restless","seconds":240},{"dateTime":"2018-06-04T07:02:00.000","level":"awake","seconds":60},{"dateTime":"2018-06-04T07:03:00.000","level":"restless","seconds":60},{"dateTime":"2018-06-04T07:04:00.000","level":"asleep","seconds":6240}],"summary":{"asleep":{"count":0,"minutes":464},"awake":{"count":2,"minutes":4},"restless":{"count":12,"minutes":19}}},"logId":18462237268,"minutesAfterWakeup":0,"minutesAsleep":464,"minutesAwake":23,"minutesToFallAsleep":0,"startTime":"2018-06-04T00:41:00.000","timeInBed":487,"type":"classic"}],"summary":{"stages":{"deep":79,"light":192,"rem":156,"wake":56},"totalMinutesAsleep":464,"totalSleepRecords":1,"totalTimeInBed":487},"fitbit-rate-limit-limit":"150","fitbit-rate-limit-remaining":"61","fitbit-rate-limit-reset":"1122"}